[
  {
    "Name": "CREATE",
    "Start": 0,
    "End": 6,
    "Text": "CREATE"
  },
  {
    "Name": "TABLE",
    "Start": 7,
    "End": 12,
    "Text": "TABLE"
  },
  {
    "Name": "IDENT",
    "Start": 13,
    "End": 18,
    "Text": "tests"
  },
  {
    "Name": "ASCII_40",
    "Start": 19,
    "End": 20,
    "Text": "("
  },
  {
    "Name": "IDENT",
    "Start": 25,
    "End": 32,
    "Text": "subject"
  },
  {
    "Name": "TEXT_P",
    "Start": 33,
    "End": 37,
    "Text": "text"
  },
  {
    "Name": "ASCII_44",
    "Start": 37,
    "End": 38,
    "Text": ","
  },
  {
    "Name": "IDENT",
    "Start": 43,
    "End": 49,
    "Text": "target"
  },
  {
    "Name": "TEXT_P",
    "Start": 50,
    "End": 54,
    "Text": "text"
  },
  {
    "Name": "ASCII_44",
    "Start": 54,
    "End": 55,
    "Text": ","
  },
  {
    "Name": "IDENT",
    "Start": 60,
    "End": 67,
    "Text": "success"
  },
  {
    "Name": "BOOLEAN_P",
    "Start": 68,
    "End": 75,
    "Text": "boolean"
  },
  {
    "Name": "ASCII_44",
    "Start": 75,
    "End": 76,
    "Text": ","
  },
  {
    "Name": "DOT_DOT",
    "Start": 81,
    "End": 83,
    "Text": ".."
  },
  {
    "Name": "ASCII_46",
    "Start": 83,
    "End": 84,
    "Text": "."
  },
  {
    "Name": "ASCII_41",
    "Start": 85,
    "End": 86,
    "Text": ")"
  },
  {
    "Name": "ASCII_59",
    "Start": 86,
    "End": 87,
    "Text": ";"
  },
  {
    "Name": "CREATE",
    "Start": 89,
    "End": 95,
    "Text": "CREATE"
  },
  {
    "Name": "UNIQUE",
    "Start": 96,
    "End": 102,
    "Text": "UNIQUE"
  },
  {
    "Name": "INDEX",
    "Start": 103,
    "End": 108,
    "Text": "INDEX"
  },
  {
    "Name": "IDENT",
    "Start": 109,
    "End": 133,
    "Text": "tests_success_constraint"
  },
  {
    "Name": "ON",
    "Start": 134,
    "End": 136,
    "Text": "ON"
  },
  {
    "Name": "IDENT",
    "Start": 137,
    "End": 142,
    "Text": "tests"
  },
  {
    "Name": "ASCII_40",
    "Start": 143,
    "End": 144,
    "Text": "("
  },
  {
    "Name": "IDENT",
    "Start": 144,
    "End": 151,
    "Text": "subject"
  },
  {
    "Name": "ASCII_44",
    "Start": 151,
    "End": 152,
    "Text": ","
  },
  {
    "Name": "IDENT",
    "Start": 153,
    "End": 159,
    "Text": "target"
  },
  {
    "Name": "ASCII_41",
    "Start": 159,
    "End": 160,
    "Text": ")"
  },
  {
    "Name": "WHERE",
    "Start": 165,
    "End": 170,
    "Text": "WHERE"
  },
  {
    "Name": "IDENT",
    "Start": 171,
    "End": 178,
    "Text": "success"
  },
  {
    "Name": "ASCII_59",
    "Start": 178,
    "End": 179,
    "Text": ";"
  }
]