[
  {
    "Name": "SET",
    "Start": 0,
    "End": 3,
    "Text": "SET"
  },
  {
    "Name": "IDENT",
    "Start": 4,
    "End": 15,
    "Text": "search_path"
  },
  {
    "Name": "ASCII_61",
    "Start": 16,
    "End": 17,
    "Text": "="
  },
  {
    "Name": "IDENT",
    "Start": 18,
    "End": 24,
    "Text": "addons"
  },
  {
    "Name": "ASCII_59",
    "Start": 24,
    "End": 25,
    "Text": ";"
  },
  {
    "Name": "CREATE",
    "Start": 26,
    "End": 32,
    "Text": "CREATE"
  },
  {
    "Name": "EXTENSION",
    "Start": 33,
    "End": 42,
    "Text": "EXTENSION"
  },
  {
    "Name": "IDENT",
    "Start": 43,
    "End": 49,
    "Text": "hstore"
  },
  {
    "Name": "ASCII_59",
    "Start": 49,
    "End": 50,
    "Text": ";"
  }
]