{
  "stmts": [
    {
      "stmt": {
        "DefineStmt": {
          "args": [
            {
              "List": {
                "items": [
                  {
                    "FunctionParameter": {
                      "argType": {
                        "location": 22,
                        "names": [
                          {
                            "String": {
                              "str": "float8"
                            }
                          }
                        ],
                        "typemod": -1
                      },
                      "mode": "FUNC_PARAM_IN"
                    }
                  }
                ]
              }
            },
            {
              "Integer": {
                "ival": -1
              }
            }
          ],
          "definition": [
            {
              "DefElem": {
                "arg": {
                  "TypeName": {
                    "location": 44,
                    "names": [
                      {
                        "String": {
                          "str": "float8_accum"
                        }
                      }
                    ],
                    "typemod": -1
                  }
                },
                "defaction": "DEFELEM_UNSPEC",
                "defname": "sfunc",
                "location": 36
              }
            },
            {
              "DefElem": {
                "arg": {
                  "TypeName": {
                    "arrayBounds": [
                      {
                        "Integer": {
                          "ival": -1
                        }
                      }
                    ],
                    "location": 70,
                    "names": [
                      {
                        "String": {
                          "str": "float8"
                        }
                      }
                    ],
                    "typemod": -1
                  }
                },
                "defaction": "DEFELEM_UNSPEC",
                "defname": "stype",
                "location": 62
              }
            },
            {
              "DefElem": {
                "arg": {
                  "TypeName": {
                    "location": 96,
                    "names": [
                      {
                        "String": {
                          "str": "float8_avg"
                        }
                      }
                    ],
                    "typemod": -1
                  }
                },
                "defaction": "DEFELEM_UNSPEC",
                "defname": "finalfunc",
                "location": 84
              }
            },
            {
              "DefElem": {
                "arg": {
                  "String": {
                    "str": "{0,0,0}"
                  }
                },
                "defaction": "DEFELEM_UNSPEC",
                "defname": "initcond",
                "location": 112
              }
            }
          ],
          "defnames": [
            {
              "String": {
                "str": "avg"
              }
            }
          ],
          "kind": "OBJECT_AGGREGATE"
        }
      },
      "stmt_len": 134
    }
  ],
  "version": 130003
}