{
  "stmts": [
    {
      "stmt": {
        "AlterTableStmt": {
          "cmds": [
            {
              "AlterTableCmd": {
                "behavior": "DROP_RESTRICT",
                "def": {
                  "ColumnDef": {
                    "colname": "description",
                    "constraints": [
                      {
                        "Constraint": {
                          "contype": "CONSTR_CHECK",
                          "initially_valid": true,
                          "location": 49,
                          "raw_expr": {
                            "A_Expr": {
                              "kind": "AEXPR_OP",
                              "lexpr": {
                                "ColumnRef": {
                                  "fields": [
                                    {
                                      "String": {
                                        "str": "description"
                                      }
                                    }
                                  ],
                                  "location": 56
                                }
                              },
                              "location": 68,
                              "name": [
                                {
                                  "String": {
                                    "str": "\u003c\u003e"
                                  }
                                }
                              ],
                              "rexpr": {
                                "A_Const": {
                                  "location": 71,
                                  "val": {
                                    "String": {
                                      "str": ""
                                    }
                                  }
                                }
                              }
                            }
                          }
                        }
                      }
                    ],
                    "is_local": true,
                    "location": 32,
                    "typeName": {
                      "location": 44,
                      "names": [
                        {
                          "String": {
                            "str": "text"
                          }
                        }
                      ],
                      "typemod": -1
                    }
                  }
                },
                "subtype": "AT_AddColumn"
              }
            }
          ],
          "relation": {
            "inh": true,
            "location": 12,
            "relname": "products",
            "relpersistence": "p"
          },
          "relkind": "OBJECT_TABLE"
        }
      },
      "stmt_len": 74
    }
  ],
  "version": 130003
}