[
  {
    "Name": "CREATE",
    "Start": 0,
    "End": 6,
    "Text": "CREATE"
  },
  {
    "Name": "TABLE",
    "Start": 7,
    "End": 12,
    "Text": "TABLE"
  },
  {
    "Name": "IDENT",
    "Start": 13,
    "End": 19,
    "Text": "people"
  },
  {
    "Name": "ASCII_40",
    "Start": 20,
    "End": 21,
    "Text": "("
  },
  {
    "Name": "SQL_COMMENT",
    "Start": 26,
    "End": 33,
    "Text": "-- ...,"
  },
  {
    "Name": "IDENT",
    "Start": 38,
    "End": 47,
    "Text": "height_cm"
  },
  {
    "Name": "NUMERIC",
    "Start": 48,
    "End": 55,
    "Text": "numeric"
  },
  {
    "Name": "ASCII_44",
    "Start": 55,
    "End": 56,
    "Text": ","
  },
  {
    "Name": "IDENT",
    "Start": 61,
    "End": 70,
    "Text": "height_in"
  },
  {
    "Name": "NUMERIC",
    "Start": 71,
    "End": 78,
    "Text": "numeric"
  },
  {
    "Name": "GENERATED",
    "Start": 79,
    "End": 88,
    "Text": "GENERATED"
  },
  {
    "Name": "ALWAYS",
    "Start": 89,
    "End": 95,
    "Text": "ALWAYS"
  },
  {
    "Name": "AS",
    "Start": 96,
    "End": 98,
    "Text": "AS"
  },
  {
    "Name": "ASCII_40",
    "Start": 99,
    "End": 100,
    "Text": "("
  },
  {
    "Name": "IDENT",
    "Start": 100,
    "End": 109,
    "Text": "height_cm"
  },
  {
    "Name": "ASCII_47",
    "Start": 110,
    "End": 111,
    "Text": "/"
  },
  {
    "Name": "FCONST",
    "Start": 112,
    "End": 116,
    "Text": "2.54"
  },
  {
    "Name": "ASCII_41",
    "Start": 116,
    "End": 117,
    "Text": ")"
  },
  {
    "Name": "STORED",
    "Start": 118,
    "End": 124,
    "Text": "STORED"
  },
  {
    "Name": "ASCII_41",
    "Start": 125,
    "End": 126,
    "Text": ")"
  },
  {
    "Name": "ASCII_59",
    "Start": 126,
    "End": 127,
    "Text": ";"
  }
]