[
  {
    "Name": "CREATE",
    "Start": 0,
    "End": 6,
    "Text": "CREATE"
  },
  {
    "Name": "PROCEDURE",
    "Start": 7,
    "End": 16,
    "Text": "PROCEDURE"
  },
  {
    "Name": "IDENT",
    "Start": 17,
    "End": 30,
    "Text": "sum_n_product"
  },
  {
    "Name": "ASCII_40",
    "Start": 30,
    "End": 31,
    "Text": "("
  },
  {
    "Name": "IDENT",
    "Start": 31,
    "End": 32,
    "Text": "x"
  },
  {
    "Name": "INT_P",
    "Start": 33,
    "End": 36,
    "Text": "int"
  },
  {
    "Name": "ASCII_44",
    "Start": 36,
    "End": 37,
    "Text": ","
  },
  {
    "Name": "IDENT",
    "Start": 38,
    "End": 39,
    "Text": "y"
  },
  {
    "Name": "INT_P",
    "Start": 40,
    "End": 43,
    "Text": "int"
  },
  {
    "Name": "ASCII_44",
    "Start": 43,
    "End": 44,
    "Text": ","
  },
  {
    "Name": "OUT_P",
    "Start": 45,
    "End": 48,
    "Text": "OUT"
  },
  {
    "Name": "IDENT",
    "Start": 49,
    "End": 52,
    "Text": "sum"
  },
  {
    "Name": "INT_P",
    "Start": 53,
    "End": 56,
    "Text": "int"
  },
  {
    "Name": "ASCII_44",
    "Start": 56,
    "End": 57,
    "Text": ","
  },
  {
    "Name": "OUT_P",
    "Start": 58,
    "End": 61,
    "Text": "OUT"
  },
  {
    "Name": "IDENT",
    "Start": 62,
    "End": 66,
    "Text": "prod"
  },
  {
    "Name": "INT_P",
    "Start": 67,
    "End": 70,
    "Text": "int"
  },
  {
    "Name": "ASCII_41",
    "Start": 70,
    "End": 71,
    "Text": ")"
  },
  {
    "Name": "AS",
    "Start": 72,
    "End": 74,
    "Text": "AS"
  },
  {
    "Name": "SCONST",
    "Start": 75,
    "End": 128,
    "Text": "$$\nBEGIN\n    sum := x + y;\n    prod := x * y;\nEND;\n$$"
  },
  {
    "Name": "LANGUAGE",
    "Start": 129,
    "End": 137,
    "Text": "LANGUAGE"
  },
  {
    "Name": "IDENT",
    "Start": 138,
    "End": 145,
    "Text": "plpgsql"
  },
  {
    "Name": "ASCII_59",
    "Start": 145,
    "End": 146,
    "Text": ";"
  }
]