{
  "stmts": [
    {
      "stmt": {
        "CreateStmt": {
          "oncommit": "ONCOMMIT_NOOP",
          "relation": {
            "inh": true,
            "location": 13,
            "relname": "test",
            "relpersistence": "p"
          },
          "tableElts": [
            {
              "ColumnDef": {
                "colname": "col1",
                "is_local": true,
                "location": 19,
                "typeName": {
                  "location": 24,
                  "names": [
                    {
                      "String": {
                        "str": "pg_catalog"
                      }
                    },
                    {
                      "String": {
                        "str": "int4"
                      }
                    }
                  ],
                  "typemod": -1
                }
              }
            },
            {
              "ColumnDef": {
                "colname": "col2",
                "is_local": true,
                "location": 33,
                "typeName": {
                  "location": 38,
                  "names": [
                    {
                      "String": {
                        "str": "text"
                      }
                    }
                  ],
                  "typemod": -1
                }
              }
            },
            {
              "ColumnDef": {
                "colname": "col3",
                "is_local": true,
                "location": 44,
                "typeName": {
                  "location": 49,
                  "names": [
                    {
                      "String": {
                        "str": "text"
                      }
                    }
                  ],
                  "typemod": -1
                }
              }
            }
          ]
        }
      },
      "stmt_len": 54
    },
    {
      "stmt": {
        "InsertStmt": {
          "override": "OVERRIDING_NOT_SET",
          "relation": {
            "inh": true,
            "location": 68,
            "relname": "test",
            "relpersistence": "p"
          },
          "selectStmt": {
            "SelectStmt": {
              "limitOption": "LIMIT_OPTION_DEFAULT",
              "op": "SETOP_NONE",
              "valuesLists": [
                {
                  "List": {
                    "items": [
                      {
                        "A_Const": {
                          "location": 81,
                          "val": {
                            "Integer": {
                              "ival": 123
                            }
                          }
                        }
                      },
                      {
                        "A_Const": {
                          "location": 86,
                          "val": {
                            "String": {
                              "str": "foo"
                            }
                          }
                        }
                      },
                      {
                        "A_Const": {
                          "location": 93,
                          "val": {
                            "String": {
                              "str": "bar"
                            }
                          }
                        }
                      }
                    ]
                  }
                }
              ]
            }
          }
        }
      },
      "stmt_len": 44,
      "stmt_location": 55
    },
    {
      "stmt": {
        "SelectStmt": {
          "fromClause": [
            {
              "RangeSubselect": {
                "alias": {
                  "aliasname": "s"
                },
                "subquery": {
                  "SelectStmt": {
                    "fromClause": [
                      {
                        "RangeVar": {
                          "alias": {
                            "aliasname": "t"
                          },
                          "inh": true,
                          "location": 159,
                          "relname": "test",
                          "relpersistence": "p"
                        }
                      }
                    ],
                    "limitOption": "LIMIT_OPTION_DEFAULT",
                    "op": "SETOP_NONE",
                    "targetList": [
                      {
                        "ResTarget": {
                          "location": 128,
                          "name": "r",
                          "val": {
                            "A_Expr": {
                              "kind": "AEXPR_OP",
                              "lexpr": {
                                "ColumnRef": {
                                  "fields": [
                                    {
                                      "String": {
                                        "str": "t"
                                      }
                                    }
                                  ],
                                  "location": 128
                                }
                              },
                              "location": 130,
                              "name": [
                                {
                                  "String": {
                                    "str": "#="
                                  }
                                }
                              ],
                              "rexpr": {
                                "A_Const": {
                                  "location": 133,
                                  "val": {
                                    "String": {
                                      "str": "\"col3\"=\u003e\"baz\""
                                    }
                                  }
                                }
                              }
                            }
                          }
                        }
                      }
                    ]
                  }
                }
              }
            }
          ],
          "limitOption": "LIMIT_OPTION_DEFAULT",
          "op": "SETOP_NONE",
          "targetList": [
            {
              "ResTarget": {
                "location": 109,
                "val": {
                  "A_Indirection": {
                    "arg": {
                      "ColumnRef": {
                        "fields": [
                          {
                            "String": {
                              "str": "r"
                            }
                          }
                        ],
                        "location": 110
                      }
                    },
                    "indirection": [
                      {
                        "A_Star": {}
                      }
                    ]
                  }
                }
              }
            }
          ]
        }
      },
      "stmt_len": 68,
      "stmt_location": 100
    }
  ],
  "version": 130003
}