{
  "stmts": [
    {
      "stmt": {
        "SelectStmt": {
          "fromClause": [
            {
              "RangeVar": {
                "inh": true,
                "location": 64,
                "relname": "households",
                "relpersistence": "p"
              }
            }
          ],
          "limitOption": "LIMIT_OPTION_DEFAULT",
          "op": "SETOP_NONE",
          "targetList": [
            {
              "ResTarget": {
                "location": 7,
                "val": {
                  "FuncCall": {
                    "agg_order": [
                      {
                        "SortBy": {
                          "location": -1,
                          "node": {
                            "ColumnRef": {
                              "fields": [
                                {
                                  "String": {
                                    "str": "income"
                                  }
                                }
                              ],
                              "location": 51
                            }
                          },
                          "sortby_dir": "SORTBY_DEFAULT",
                          "sortby_nulls": "SORTBY_NULLS_DEFAULT"
                        }
                      }
                    ],
                    "agg_within_group": true,
                    "args": [
                      {
                        "A_Const": {
                          "location": 23,
                          "val": {
                            "Float": {
                              "str": "0.5"
                            }
                          }
                        }
                      }
                    ],
                    "funcname": [
                      {
                        "String": {
                          "str": "percentile_cont"
                        }
                      }
                    ],
                    "location": 7
                  }
                }
              }
            }
          ]
        }
      },
      "stmt_len": 74
    }
  ],
  "version": 130003
}