[
  {
    "Name": "IDENT",
    "Start": 0,
    "End": 11,
    "Text": "selectivity"
  },
  {
    "Name": "ASCII_61",
    "Start": 12,
    "End": 13,
    "Text": "="
  },
  {
    "Name": "ASCII_40",
    "Start": 14,
    "End": 15,
    "Text": "("
  },
  {
    "Name": "ICONST",
    "Start": 15,
    "End": 16,
    "Text": "1"
  },
  {
    "Name": "ASCII_43",
    "Start": 17,
    "End": 18,
    "Text": "+"
  },
  {
    "Name": "ASCII_40",
    "Start": 19,
    "End": 20,
    "Text": "("
  },
  {
    "Name": "ICONST",
    "Start": 20,
    "End": 24,
    "Text": "1000"
  },
  {
    "Name": "ASCII_45",
    "Start": 25,
    "End": 26,
    "Text": "-"
  },
  {
    "Name": "IDENT",
    "Start": 27,
    "End": 33,
    "Text": "bucket"
  },
  {
    "Name": "ASCII_91",
    "Start": 33,
    "End": 34,
    "Text": "["
  },
  {
    "Name": "ICONST",
    "Start": 34,
    "End": 35,
    "Text": "2"
  },
  {
    "Name": "ASCII_93",
    "Start": 35,
    "End": 36,
    "Text": "]"
  },
  {
    "Name": "ASCII_46",
    "Start": 36,
    "End": 37,
    "Text": "."
  },
  {
    "Name": "IDENT",
    "Start": 37,
    "End": 40,
    "Text": "min"
  },
  {
    "Name": "ASCII_41",
    "Start": 40,
    "End": 41,
    "Text": ")"
  },
  {
    "Name": "ASCII_47",
    "Start": 41,
    "End": 42,
    "Text": "/"
  },
  {
    "Name": "ASCII_40",
    "Start": 42,
    "End": 43,
    "Text": "("
  },
  {
    "Name": "IDENT",
    "Start": 43,
    "End": 49,
    "Text": "bucket"
  },
  {
    "Name": "ASCII_91",
    "Start": 49,
    "End": 50,
    "Text": "["
  },
  {
    "Name": "ICONST",
    "Start": 50,
    "End": 51,
    "Text": "2"
  },
  {
    "Name": "ASCII_93",
    "Start": 51,
    "End": 52,
    "Text": "]"
  },
  {
    "Name": "ASCII_46",
    "Start": 52,
    "End": 53,
    "Text": "."
  },
  {
    "Name": "IDENT",
    "Start": 53,
    "End": 56,
    "Text": "max"
  },
  {
    "Name": "ASCII_45",
    "Start": 57,
    "End": 58,
    "Text": "-"
  },
  {
    "Name": "IDENT",
    "Start": 59,
    "End": 65,
    "Text": "bucket"
  },
  {
    "Name": "ASCII_91",
    "Start": 65,
    "End": 66,
    "Text": "["
  },
  {
    "Name": "ICONST",
    "Start": 66,
    "End": 67,
    "Text": "2"
  },
  {
    "Name": "ASCII_93",
    "Start": 67,
    "End": 68,
    "Text": "]"
  },
  {
    "Name": "ASCII_46",
    "Start": 68,
    "End": 69,
    "Text": "."
  },
  {
    "Name": "IDENT",
    "Start": 69,
    "End": 72,
    "Text": "min"
  },
  {
    "Name": "ASCII_41",
    "Start": 72,
    "End": 73,
    "Text": ")"
  },
  {
    "Name": "ASCII_41",
    "Start": 73,
    "End": 74,
    "Text": ")"
  },
  {
    "Name": "ASCII_47",
    "Start": 74,
    "End": 75,
    "Text": "/"
  },
  {
    "Name": "IDENT",
    "Start": 75,
    "End": 86,
    "Text": "num_buckets"
  },
  {
    "Name": "ASCII_61",
    "Start": 99,
    "End": 100,
    "Text": "="
  },
  {
    "Name": "ASCII_40",
    "Start": 101,
    "End": 102,
    "Text": "("
  },
  {
    "Name": "ICONST",
    "Start": 102,
    "End": 103,
    "Text": "1"
  },
  {
    "Name": "ASCII_43",
    "Start": 104,
    "End": 105,
    "Text": "+"
  },
  {
    "Name": "ASCII_40",
    "Start": 106,
    "End": 107,
    "Text": "("
  },
  {
    "Name": "ICONST",
    "Start": 107,
    "End": 111,
    "Text": "1000"
  },
  {
    "Name": "ASCII_45",
    "Start": 112,
    "End": 113,
    "Text": "-"
  },
  {
    "Name": "ICONST",
    "Start": 114,
    "End": 117,
    "Text": "993"
  },
  {
    "Name": "ASCII_41",
    "Start": 117,
    "End": 118,
    "Text": ")"
  },
  {
    "Name": "ASCII_47",
    "Start": 118,
    "End": 119,
    "Text": "/"
  },
  {
    "Name": "ASCII_40",
    "Start": 119,
    "End": 120,
    "Text": "("
  },
  {
    "Name": "ICONST",
    "Start": 120,
    "End": 124,
    "Text": "1997"
  },
  {
    "Name": "ASCII_45",
    "Start": 125,
    "End": 126,
    "Text": "-"
  },
  {
    "Name": "ICONST",
    "Start": 127,
    "End": 130,
    "Text": "993"
  },
  {
    "Name": "ASCII_41",
    "Start": 130,
    "End": 131,
    "Text": ")"
  },
  {
    "Name": "ASCII_41",
    "Start": 131,
    "End": 132,
    "Text": ")"
  },
  {
    "Name": "ASCII_47",
    "Start": 132,
    "End": 133,
    "Text": "/"
  },
  {
    "Name": "ICONST",
    "Start": 133,
    "End": 135,
    "Text": "10"
  },
  {
    "Name": "ASCII_61",
    "Start": 148,
    "End": 149,
    "Text": "="
  },
  {
    "Name": "FCONST",
    "Start": 150,
    "End": 158,
    "Text": "0.100697"
  }
]