[
  {
    "Name": "CREATE",
    "Start": 0,
    "End": 6,
    "Text": "CREATE"
  },
  {
    "Name": "UNIQUE",
    "Start": 7,
    "End": 13,
    "Text": "UNIQUE"
  },
  {
    "Name": "INDEX",
    "Start": 14,
    "End": 19,
    "Text": "INDEX"
  },
  {
    "Name": "IDENT",
    "Start": 20,
    "End": 44,
    "Text": "tests_success_constraint"
  },
  {
    "Name": "ON",
    "Start": 45,
    "End": 47,
    "Text": "ON"
  },
  {
    "Name": "IDENT",
    "Start": 48,
    "End": 53,
    "Text": "tests"
  },
  {
    "Name": "ASCII_40",
    "Start": 54,
    "End": 55,
    "Text": "("
  },
  {
    "Name": "IDENT",
    "Start": 55,
    "End": 62,
    "Text": "subject"
  },
  {
    "Name": "ASCII_44",
    "Start": 62,
    "End": 63,
    "Text": ","
  },
  {
    "Name": "IDENT",
    "Start": 64,
    "End": 70,
    "Text": "target"
  },
  {
    "Name": "ASCII_41",
    "Start": 70,
    "End": 71,
    "Text": ")"
  },
  {
    "Name": "WHERE",
    "Start": 76,
    "End": 81,
    "Text": "WHERE"
  },
  {
    "Name": "IDENT",
    "Start": 82,
    "End": 89,
    "Text": "success"
  },
  {
    "Name": "ASCII_59",
    "Start": 89,
    "End": 90,
    "Text": ";"
  }
]