{
  "stmts": [
    {
      "stmt": {
        "DefineStmt": {
          "definition": [
            {
              "DefElem": {
                "arg": {
                  "TypeName": {
                    "location": 52,
                    "names": [
                      {
                        "String": {
                          "str": "pg_catalog"
                        }
                      },
                      {
                        "String": {
                          "str": "english"
                        }
                      }
                    ],
                    "typemod": -1
                  }
                },
                "defaction": "DEFELEM_UNSPEC",
                "defname": "copy",
                "location": 45
              }
            }
          ],
          "defnames": [
            {
              "String": {
                "str": "public"
              }
            },
            {
              "String": {
                "str": "pg"
              }
            }
          ],
          "kind": "OBJECT_TSCONFIGURATION"
        }
      },
      "stmt_len": 72
    }
  ],
  "version": 130003
}