[
  {
    "Name": "SELECT",
    "Start": 0,
    "End": 6,
    "Text": "SELECT"
  },
  {
    "Name": "IDENT",
    "Start": 7,
    "End": 15,
    "Text": "somefunc"
  },
  {
    "Name": "ASCII_40",
    "Start": 15,
    "End": 16,
    "Text": "("
  },
  {
    "Name": "IDENT",
    "Start": 16,
    "End": 17,
    "Text": "c"
  },
  {
    "Name": "ASCII_41",
    "Start": 17,
    "End": 18,
    "Text": ")"
  },
  {
    "Name": "FROM",
    "Start": 19,
    "End": 23,
    "Text": "FROM"
  },
  {
    "Name": "IDENT",
    "Start": 24,
    "End": 38,
    "Text": "inventory_item"
  },
  {
    "Name": "IDENT",
    "Start": 39,
    "End": 40,
    "Text": "c"
  },
  {
    "Name": "ASCII_59",
    "Start": 40,
    "End": 41,
    "Text": ";"
  },
  {
    "Name": "SELECT",
    "Start": 42,
    "End": 48,
    "Text": "SELECT"
  },
  {
    "Name": "IDENT",
    "Start": 49,
    "End": 57,
    "Text": "somefunc"
  },
  {
    "Name": "ASCII_40",
    "Start": 57,
    "End": 58,
    "Text": "("
  },
  {
    "Name": "IDENT",
    "Start": 58,
    "End": 59,
    "Text": "c"
  },
  {
    "Name": "ASCII_46",
    "Start": 59,
    "End": 60,
    "Text": "."
  },
  {
    "Name": "ASCII_42",
    "Start": 60,
    "End": 61,
    "Text": "*"
  },
  {
    "Name": "ASCII_41",
    "Start": 61,
    "End": 62,
    "Text": ")"
  },
  {
    "Name": "FROM",
    "Start": 63,
    "End": 67,
    "Text": "FROM"
  },
  {
    "Name": "IDENT",
    "Start": 68,
    "End": 82,
    "Text": "inventory_item"
  },
  {
    "Name": "IDENT",
    "Start": 83,
    "End": 84,
    "Text": "c"
  },
  {
    "Name": "ASCII_59",
    "Start": 84,
    "End": 85,
    "Text": ";"
  },
  {
    "Name": "SELECT",
    "Start": 86,
    "End": 92,
    "Text": "SELECT"
  },
  {
    "Name": "IDENT",
    "Start": 93,
    "End": 94,
    "Text": "c"
  },
  {
    "Name": "ASCII_46",
    "Start": 94,
    "End": 95,
    "Text": "."
  },
  {
    "Name": "IDENT",
    "Start": 95,
    "End": 103,
    "Text": "somefunc"
  },
  {
    "Name": "FROM",
    "Start": 104,
    "End": 108,
    "Text": "FROM"
  },
  {
    "Name": "IDENT",
    "Start": 109,
    "End": 123,
    "Text": "inventory_item"
  },
  {
    "Name": "IDENT",
    "Start": 124,
    "End": 125,
    "Text": "c"
  },
  {
    "Name": "ASCII_59",
    "Start": 125,
    "End": 126,
    "Text": ";"
  }
]