[
  {
    "Name": "DECLARE",
    "Start": 0,
    "End": 7,
    "Text": "DECLARE"
  },
  {
    "Name": "IDENT",
    "Start": 10,
    "End": 19,
    "Text": "text_var1"
  },
  {
    "Name": "TEXT_P",
    "Start": 20,
    "End": 24,
    "Text": "text"
  },
  {
    "Name": "ASCII_59",
    "Start": 24,
    "End": 25,
    "Text": ";"
  },
  {
    "Name": "IDENT",
    "Start": 28,
    "End": 37,
    "Text": "text_var2"
  },
  {
    "Name": "TEXT_P",
    "Start": 38,
    "End": 42,
    "Text": "text"
  },
  {
    "Name": "ASCII_59",
    "Start": 42,
    "End": 43,
    "Text": ";"
  },
  {
    "Name": "IDENT",
    "Start": 46,
    "End": 55,
    "Text": "text_var3"
  },
  {
    "Name": "TEXT_P",
    "Start": 56,
    "End": 60,
    "Text": "text"
  },
  {
    "Name": "ASCII_59",
    "Start": 60,
    "End": 61,
    "Text": ";"
  },
  {
    "Name": "BEGIN_P",
    "Start": 62,
    "End": 67,
    "Text": "BEGIN"
  },
  {
    "Name": "SQL_COMMENT",
    "Start": 70,
    "End": 119,
    "Text": "-- some processing which might cause an exception"
  },
  {
    "Name": "DOT_DOT",
    "Start": 122,
    "End": 124,
    "Text": ".."
  },
  {
    "Name": "ASCII_46",
    "Start": 124,
    "End": 125,
    "Text": "."
  },
  {
    "Name": "IDENT",
    "Start": 126,
    "End": 135,
    "Text": "EXCEPTION"
  },
  {
    "Name": "WHEN",
    "Start": 136,
    "End": 140,
    "Text": "WHEN"
  },
  {
    "Name": "OTHERS",
    "Start": 141,
    "End": 147,
    "Text": "OTHERS"
  },
  {
    "Name": "THEN",
    "Start": 148,
    "End": 152,
    "Text": "THEN"
  },
  {
    "Name": "IDENT",
    "Start": 155,
    "End": 158,
    "Text": "GET"
  },
  {
    "Name": "IDENT",
    "Start": 159,
    "End": 166,
    "Text": "STACKED"
  },
  {
    "Name": "IDENT",
    "Start": 167,
    "End": 178,
    "Text": "DIAGNOSTICS"
  },
  {
    "Name": "IDENT",
    "Start": 179,
    "End": 188,
    "Text": "text_var1"
  },
  {
    "Name": "ASCII_61",
    "Start": 189,
    "End": 190,
    "Text": "="
  },
  {
    "Name": "IDENT",
    "Start": 191,
    "End": 203,
    "Text": "MESSAGE_TEXT"
  },
  {
    "Name": "ASCII_44",
    "Start": 203,
    "End": 204,
    "Text": ","
  },
  {
    "Name": "IDENT",
    "Start": 231,
    "End": 240,
    "Text": "text_var2"
  },
  {
    "Name": "ASCII_61",
    "Start": 241,
    "End": 242,
    "Text": "="
  },
  {
    "Name": "IDENT",
    "Start": 243,
    "End": 262,
    "Text": "PG_EXCEPTION_DETAIL"
  },
  {
    "Name": "ASCII_44",
    "Start": 262,
    "End": 263,
    "Text": ","
  },
  {
    "Name": "IDENT",
    "Start": 290,
    "End": 299,
    "Text": "text_var3"
  },
  {
    "Name": "ASCII_61",
    "Start": 300,
    "End": 301,
    "Text": "="
  },
  {
    "Name": "IDENT",
    "Start": 302,
    "End": 319,
    "Text": "PG_EXCEPTION_HINT"
  },
  {
    "Name": "ASCII_59",
    "Start": 319,
    "End": 320,
    "Text": ";"
  },
  {
    "Name": "END_P",
    "Start": 321,
    "End": 324,
    "Text": "END"
  },
  {
    "Name": "ASCII_59",
    "Start": 324,
    "End": 325,
    "Text": ";"
  }
]