{
  "stmts": [
    {
      "stmt": {
        "InsertStmt": {
          "override": "OVERRIDING_NOT_SET",
          "relation": {
            "inh": true,
            "location": 12,
            "relname": "cities",
            "relpersistence": "p"
          },
          "selectStmt": {
            "SelectStmt": {
              "limitOption": "LIMIT_OPTION_DEFAULT",
              "op": "SETOP_NONE",
              "valuesLists": [
                {
                  "List": {
                    "items": [
                      {
                        "A_Const": {
                          "location": 27,
                          "val": {
                            "String": {
                              "str": "San Francisco"
                            }
                          }
                        }
                      },
                      {
                        "A_Const": {
                          "location": 44,
                          "val": {
                            "String": {
                              "str": "(-194.0, 53.0)"
                            }
                          }
                        }
                      }
                    ]
                  }
                }
              ]
            }
          }
        }
      },
      "stmt_len": 61
    }
  ],
  "version": 130003
}