{
  "stmts": [
    {
      "stmt": {
        "CreateStmt": {
          "inhRelations": [
            {
              "RangeVar": {
                "inh": true,
                "location": 36,
                "relname": "orders",
                "relpersistence": "p"
              }
            }
          ],
          "oncommit": "ONCOMMIT_NOOP",
          "partbound": {
            "location": 58,
            "modulus": 4,
            "strategy": "h"
          },
          "relation": {
            "inh": true,
            "location": 13,
            "relname": "orders_p1",
            "relpersistence": "p"
          }
        }
      },
      "stmt_len": 87
    },
    {
      "stmt": {
        "CreateStmt": {
          "inhRelations": [
            {
              "RangeVar": {
                "inh": true,
                "location": 125,
                "relname": "orders",
                "relpersistence": "p"
              }
            }
          ],
          "oncommit": "ONCOMMIT_NOOP",
          "partbound": {
            "location": 147,
            "modulus": 4,
            "remainder": 1,
            "strategy": "h"
          },
          "relation": {
            "inh": true,
            "location": 102,
            "relname": "orders_p2",
            "relpersistence": "p"
          }
        }
      },
      "stmt_len": 88,
      "stmt_location": 88
    },
    {
      "stmt": {
        "CreateStmt": {
          "inhRelations": [
            {
              "RangeVar": {
                "inh": true,
                "location": 214,
                "relname": "orders",
                "relpersistence": "p"
              }
            }
          ],
          "oncommit": "ONCOMMIT_NOOP",
          "partbound": {
            "location": 236,
            "modulus": 4,
            "remainder": 2,
            "strategy": "h"
          },
          "relation": {
            "inh": true,
            "location": 191,
            "relname": "orders_p3",
            "relpersistence": "p"
          }
        }
      },
      "stmt_len": 88,
      "stmt_location": 177
    },
    {
      "stmt": {
        "CreateStmt": {
          "inhRelations": [
            {
              "RangeVar": {
                "inh": true,
                "location": 303,
                "relname": "orders",
                "relpersistence": "p"
              }
            }
          ],
          "oncommit": "ONCOMMIT_NOOP",
          "partbound": {
            "location": 325,
            "modulus": 4,
            "remainder": 3,
            "strategy": "h"
          },
          "relation": {
            "inh": true,
            "location": 280,
            "relname": "orders_p4",
            "relpersistence": "p"
          }
        }
      },
      "stmt_len": 88,
      "stmt_location": 266
    }
  ],
  "version": 130003
}